setup.py
hklab2024kopo/__init__.py
hklab2024kopo/commonFunction.py
hklab2024kopo.egg-info/PKG-INFO
hklab2024kopo.egg-info/SOURCES.txt
hklab2024kopo.egg-info/dependency_links.txt
hklab2024kopo.egg-info/requires.txt
hklab2024kopo.egg-info/top_level.txt